scikit_groups-0.8.dist-info/DESCRIPTION.rst
scikit_groups-0.8.dist-info/METADATA
scikit_groups-0.8.dist-info/RECORD
scikit_groups-0.8.dist-info/WHEEL
scikit_groups-0.8.dist-info/metadata.json
scikit_groups-0.8.dist-info/top_level.txt
skgroups/__init__.py
skgroups/groups.py
skgroups/pure.py
