Metadata-Version: 2.0
Name: scikit-groups
Version: 0.8
Summary: An package for constructing finite abelian groups
Home-page: https://github.com/smeths/scikit-groups
Author: John Smethurst
Author-email: johnsmethurst@gmail.com
License: MIT
Platform: UNKNOWN
